{
  "lastSync": "2026-01-23T05:18:37.692900",
  "mode": "daily",
  "today": {
    "date": "2026-01-23",
    "source": "garmin",
    "fetchedAt": "2026-01-23T05:18:36.417393",
    "hrv": 43,
    "rhr": 55,
    "stressAvg": 17,
    "respiration": 14.0,
    "sleepDuration": 420,
    "sleepDeep": 111,
    "sleepLight": 300,
    "sleepRem": 9,
    "sleepAwake": 10,
    "sleepScore": 62,
    "sleepInterruptions": 1,
    "steps": 128,
    "floors": null,
    "intensityMinutes": 0,
    "weight": null,
    "bmi": null,
    "bodyFat": null
  },
  "yesterday": {
    "date": "2026-01-22",
    "source": "garmin",
    "fetchedAt": "2026-01-23T05:18:37.045186",
    "hrv": 36,
    "rhr": 58,
    "stressAvg": 43,
    "respiration": 15.0,
    "sleepDuration": 344,
    "sleepDeep": 93,
    "sleepLight": 245,
    "sleepRem": 6,
    "sleepAwake": 17,
    "sleepScore": 59,
    "sleepInterruptions": 1,
    "steps": 6831,
    "floors": null,
    "intensityMinutes": 2,
    "weight": null,
    "bmi": null,
    "bodyFat": null
  },
  "history": []
}